dias/__init__.py
dias/nb_utils.py
dias/patt_matcher.py
dias/rewriter.py
dias-0.1.4.dist-info/licenses/LICENSE
dias-0.1.4.dist-info/licenses/NOTICE
dias-0.1.4.dist-info/METADATA
dias-0.1.4.dist-info/WHEEL
dias-0.1.4.dist-info/top_level.txt
dias-0.1.4.dist-info/RECORD
