Metadata-Version: 2.4
Name: dias
Version: 0.1.4
Summary: Dynamic rewriting of pandas code
Author-email: Stefanos Baziotis <sb54@illinois.edu>
Project-URL: Homepage, https://github.com/ADAPT-uiuc/dias
Classifier: Programming Language :: Python :: 3
Classifier: Operating System :: OS Independent
Requires-Python: <3.12,>=3.7
License-File: LICENSE
License-File: NOTICE
Requires-Dist: astor>=0.8.1
Requires-Dist: pandas==1.5.1
Requires-Dist: numpy==1.23.5
Requires-Dist: nbformat==5.7.0
Requires-Dist: ipython==8.7.0
Dynamic: license-file
